jupyter_plotly_dash/__init__.py
jupyter_plotly_dash/async_views.py
jupyter_plotly_dash/dash_wrapper.py
jupyter_plotly_dash/ipython.py
jupyter_plotly_dash/nbkernel.py
jupyter_plotly_dash/nbsrvext.py
jupyter_plotly_dash/version.py
jupyter_plotly_dash/serverext/__init__.py
jupyter_plotly_dash/tests/__init__.py
jupyter_plotly_dash/tests/test_imports.py
jupyter_plotly_dash-0.4.3.data/data/etc/jupyter/jupyter_notebook_config.d/jupyter-plotly-dash.json
jupyter_plotly_dash-0.4.3.dist-info/LICENSE
jupyter_plotly_dash-0.4.3.dist-info/METADATA
jupyter_plotly_dash-0.4.3.dist-info/WHEEL
jupyter_plotly_dash-0.4.3.dist-info/top_level.txt
jupyter_plotly_dash-0.4.3.dist-info/RECORD
