Metadata-Version: 2.1
Name: jupyter-plotly-dash
Version: 0.4.3
Summary: Interactive Jupyter use of plotly dash apps
Home-page: https://github.com/GibbsConsulting/jupyter-plotly-dash
Author: Gibbs Consulting
Author-email: jupyter_plotly_dash@gibbsconsulting.ca
License: MIT
Project-URL: Source, https://github.com/GibbsConsulting/jupyter-plotly-dash
Project-URL: Tracker, https://github.com/GibbsConsulting/jupyter-plotly-dash/issues
Project-URL: Documentation, http://jupyter-plotly-dash.readthedocs.io/
Keywords: Jupyter plotly plotly-dash dash dashboard django-plotly-dash Django
Platform: UNKNOWN
Classifier: Development Status :: 3 - Alpha
Classifier: Intended Audience :: Developers
Classifier: License :: OSI Approved :: GNU Affero General Public License v3
Classifier: Programming Language :: Python :: 3
Classifier: Programming Language :: Python :: 3.6
Classifier: Programming Language :: Python :: 3.7
Classifier: Framework :: Dash
Requires-Python: >=3.6
Requires-Dist: aiohttp
Requires-Dist: django-bootstrap4
Requires-Dist: django-plotly-dash
Requires-Dist: dpd-components
Requires-Dist: dpd-static-support
Requires-Dist: jupyter
Requires-Dist: nbserverproxy
